astep_form_utils/__init__.py
astep_form_utils/fields/__init__.py
astep_form_utils/fields/exceptions.py
astep_form_utils/fields/types.py
fields/__init__.py
fields/exceptions.py
fields/types.py
tests/__init__.py
tests/test_fieldset.py
astep_forms_utils-0.2.7.dist-info/LICENSE
astep_forms_utils-0.2.7.dist-info/METADATA
astep_forms_utils-0.2.7.dist-info/WHEEL
astep_forms_utils-0.2.7.dist-info/top_level.txt
astep_forms_utils-0.2.7.dist-info/RECORD
