Metadata-Version: 2.1
Name: astep-forms-utils
Version: 0.2.7
Summary: A package for utilities regarding the aSTEP 2019 rendering architecture
Home-page: https://daisy-git.cs.aau.dk/aSTEP-2019/python_form_utils
Author: Casper Weiss Bang
Author-email: master@thecdk.net
License: UNKNOWN
Platform: UNKNOWN
Classifier: Programming Language :: Python :: 3
Classifier: License :: OSI Approved :: MIT License
Classifier: Operating System :: OS Independent
